cysystemd/__init__.py
cysystemd/_daemon.cpython-310-x86_64-linux-gnu.so
cysystemd/_journal.cpython-310-x86_64-linux-gnu.so
cysystemd/async_reader.py
cysystemd/daemon.py
cysystemd/journal.py
cysystemd/py.typed
cysystemd/reader.cpython-310-x86_64-linux-gnu.so
cysystemd.libs/libcap-6500f43e.so.2.48
cysystemd.libs/libgcrypt-3098dcde.so.20.4.0
cysystemd.libs/libgpg-error-df6ee685.so.0.32.0
cysystemd.libs/liblz4-9ba322f5.so.1.9.3
cysystemd.libs/liblzma-270e41f3.so.5.2.5
cysystemd.libs/libsystemd-ac188c81.so.0.35.0
cysystemd.libs/libzstd-cde3f28d.so.1.5.1
cysystemd-2.0.1.dist-info/LICENSE
cysystemd-2.0.1.dist-info/METADATA
cysystemd-2.0.1.dist-info/WHEEL
cysystemd-2.0.1.dist-info/top_level.txt
cysystemd-2.0.1.dist-info/RECORD
